nightmare_pdf/__init__.py
nightmare_pdf/admin.py
nightmare_pdf/apps.py
nightmare_pdf/generators.py
nightmare_pdf/models.py
nightmare_pdf/render_pdf.js
nightmare_pdf/settings.py
nightmare_pdf/tests.py
nightmare_pdf/views.py
nightmare_pdf/migrations/__init__.py
nightmare_pdf-0.1.0.dist-info/DESCRIPTION.rst
nightmare_pdf-0.1.0.dist-info/METADATA
nightmare_pdf-0.1.0.dist-info/RECORD
nightmare_pdf-0.1.0.dist-info/WHEEL
nightmare_pdf-0.1.0.dist-info/metadata.json
nightmare_pdf-0.1.0.dist-info/top_level.txt
