Metadata-Version: 2.0
Name: nightmare-pdf
Version: 0.1.0
Summary: Convert HTML to pdf with django using nightmarejs
Home-page: https://github.com/charlesthk/django-nightmare-pdf
Author: Charles TISSIER
Author-email: charles@vingtcinq.io
License: MIT
Keywords: python django pdf html nightmare
Platform: UNKNOWN
Classifier: Development Status :: 5 - Production/Stable
Classifier: Intended Audience :: Developers
Classifier: Topic :: Software Development :: Libraries :: Python Modules
Classifier: License :: OSI Approved :: MIT License
Classifier: Framework :: Django :: 1.10
Classifier: Framework :: Django :: 1.9
Classifier: Programming Language :: Python :: 2
Classifier: Programming Language :: Python :: 2.3
Classifier: Programming Language :: Python :: 2.4
Classifier: Programming Language :: Python :: 2.5
Classifier: Programming Language :: Python :: 2.6
Classifier: Programming Language :: Python :: 2.7
